data_export/__init__.py
data_export/data_export.py
data_import/__init__.py
data_import/data_import.py
data_transform/__init__.py
data_transform/predef_math_functions.py
gui/__init__.py
gui/frame_design.py
sonoUno-3.0.3.data/scripts/sonoUno
sound_module/__init__.py
sound_module/simple_sound.py
sonoUno-3.0.3.dist-info/METADATA
sonoUno-3.0.3.dist-info/WHEEL
sonoUno-3.0.3.dist-info/top_level.txt
sonoUno-3.0.3.dist-info/zip-safe
sonoUno-3.0.3.dist-info/RECORD
